bel_resources/__init__.py
bel_resources/__main__.py
bel_resources/cli.py
bel_resources/constants.py
bel_resources/exc.py
bel_resources/github.py
bel_resources/obo.py
bel_resources/read_document.py
bel_resources/read_utils.py
bel_resources/utils.py
bel_resources/write_annotation.py
bel_resources/write_document.py
bel_resources/write_namespace.py
bel_resources/write_utils.py
bel_resources-0.0.3.dist-info/LICENSE
bel_resources-0.0.3.dist-info/METADATA
bel_resources-0.0.3.dist-info/WHEEL
bel_resources-0.0.3.dist-info/entry_points.txt
bel_resources-0.0.3.dist-info/top_level.txt
bel_resources-0.0.3.dist-info/zip-safe
bel_resources-0.0.3.dist-info/RECORD
