Metadata-Version: 2.1
Name: bel-resources
Version: 0.0.3
Summary: Utilities for BEL resource files.
Home-page: https://github.com/cthoyt/bel-resources
Author: Charles Tapley Hoyt
Author-email: cthoyt@gmail.com
Maintainer: Charles Tapley Hoyt
Maintainer-email: cthoyt@gmail.com
License: MIT
Download-URL: https://github.com/cthoyt/bel-resources/releases
Project-URL: Bug Tracker, https://github.com/cthoyt/bel-resources/issues
Project-URL: Source Code, https://github.com/cthoyt/bel-resources
Keywords: Biological Expression Language,BEL,Semantic Web,Networks Biology,Systems Biology,Ontologies
Platform: UNKNOWN
Classifier: Development Status :: 1 - Planning
Classifier: Intended Audience :: Developers
Classifier: License :: OSI Approved :: MIT License
Classifier: Operating System :: OS Independent
Classifier: Programming Language :: Python
Classifier: Programming Language :: Python :: 3.5
Classifier: Programming Language :: Python :: 3.6
Classifier: Programming Language :: Python :: 3.7
Classifier: Programming Language :: Python :: 3 :: Only
Requires-Python: >=3.5
Requires-Dist: requests
Requires-Dist: requests-file
Requires-Dist: multisplitby
Provides-Extra: obo
Requires-Dist: obonet ; extra == 'obo'
